{
  "providedBy": "sneaky coyote",
  "providerTwitter": "@sneaky_coyote",
  "combos": [
    {
      "starter": "d/f+2",
      "combo": "4, u, 3 ~dash~ b+2, b+2, 1 (S!) ~dash~ (During Rage) 1+2",
      "damage": 70,
      "notes": "-",
      "oki": "-",
      "volunteer": "sneaky coyote",
      "volunteer twitter": "@sneaky_coyote"
    },
    {
      "starter": "d/f+2",
      "combo": "4, u, 3 ~dash~ b+2, b+2, 1 (S!) ~dash~ 4, 3, DSS f+4",
      "damage": 62,
      "notes": "-",
      "oki": "-",
      "volunteer": "-",
      "volunteer twitter": "-"
    },
    {
      "starter": "u/f+4",
      "combo": "3+4, b+2, 1 (S!) f, F+2, 1, 3",
      "damage": 43,
      "notes": "-",
      "oki": "-",
      "volunteer": "-",
      "volunteer twitter": "-"
    },
    {
      "starter": "U/F+4",
      "combo": "u/f+1, 4, u, 3 ~dash~ b+2, 1 (S!) ~dash~ 4, 3, DSS f+4",
      "damage": 72,
      "notes": "-",
      "oki": "-",
      "volunteer": "-",
      "volunteer twitter": "-"
    },
    {
      "starter": "b+2, 3, 4",
      "combo": "f+3, 4 (S!) ~dash~ 4, 3, DSS f+3",
      "damage": 83,
      "notes": "-",
      "oki": "-",
      "volunteer": "-",
      "volunteer twitter": "-"
    },
    {
      "starter": "f, F+4, 3",
      "combo": "(B!) ~dash~ b+2, 4, u, 3, b+2, 1 (S!) ~dash~ 4, 3, DSS f+4",
      "damage": 70,
      "notes": "-",
      "oki": "-",
      "volunteer": "-",
      "volunteer twitter": "-"
    },
    {
      "starter": "3+4, 4",
      "combo": "(S!) ~dash~ 4, u, 3, 3+4, 4",
      "damage": 53,
      "notes": "-",
      "oki": "-",
      "volunteer": "-",
      "volunteer twitter": "-"
    },
    {
      "starter": "d+2, 3",
      "combo": "4, 3, 4, DSS f+3 (S!) ~dash~ 4, 3, DSS f+4",
      "damage": 76,
      "notes": "-",
      "oki": "-",
      "volunteer": "-",
      "volunteer twitter": "-"
    },
    {
      "starter": "[4]",
      "combo": "b+2, b+2, b+2, b+2, 1 (S!) ~dash~ d+2, 3",
      "damage": 50,
      "notes": "-",
      "oki": "-",
      "volunteer": "-",
      "volunteer twitter": "-"
    },
    {
      "starter": "[BT 2]",
      "combo": "b+2, 4, u, 3 ~dash~ b+2, 1 (S!) ~dash~ f, F+2, 3",
      "damage": 49,
      "notes": "-",
      "oki": "-",
      "volunteer": "-",
      "volunteer twitter": "-"
    },
    {
      "starter": "WS 2",
      "combo": "4, u, 3, 3+4, b+2, 1 (S!) ~dash~ f, F+3",
      "damage": 61
    },
    {
      "starter": "BT Opponent",
      "combo": "-",
      "damage": "-",
      "notes": "-",
      "oki": "-",
      "volunteer": "-",
      "volunteer twitter": "-"
    },
    {
      "starter": "Float",
      "combo": "-",
      "damage": "-",
      "notes": "-",
      "oki": "-",
      "volunteer": "-",
      "volunteer twitter": "-"
    },
    {
      "starter": "Floor Break Post (S!)",
      "combo": "-",
      "damage": "-",
      "notes": "-",
      "oki": "-",
      "volunteer": "-",
      "volunteer twitter": "-"
    },
    {
      "starter": "Floor Break Pre (S!)",
      "combo": "-",
      "damage": "-",
      "notes": "-",
      "oki": "-",
      "volunteer": "-",
      "volunteer twitter": "-"
    },
    {
      "starter": "Low Parry",
      "combo": "b+2, 4, u, 3, b+2, 1 (S!) ~dash~ f, F+3",
      "damage": 40,
      "notes": "-",
      "oki": "-",
      "volunteer": "-",
      "volunteer twitter": "-"
    },
    {
      "starter": "Side Float",
      "combo": "-",
      "damage": "-",
      "notes": "-",
      "oki": "-",
      "volunteer": "-",
      "volunteer twitter": "-"
    },
    {
      "starter": "Slide Punish",
      "combo": "-",
      "damage": "-",
      "notes": "-",
      "oki": "-",
      "volunteer": "-",
      "volunteer twitter": "-"
    },
    {
      "starter": "Wall Break Post (S!)",
      "combo": "-",
      "damage": "-",
      "notes": "-",
      "oki": "-",
      "volunteer": "-",
      "volunteer twitter": "-"
    },
    {
      "starter": "Wall Break Pre (S!)",
      "combo": "-",
      "damage": "-",
      "notes": "-",
      "oki": "-",
      "volunteer": "-",
      "volunteer twitter": "-"
    },
    {
      "starter": "Wall Carry",
      "combo": "-",
      "damage": "-",
      "notes": "-",
      "oki": "-",
      "volunteer": "-",
      "volunteer twitter": "-"
    },
    {
      "starter": "Wall Ender",
      "combo": "4, 3, DSS f+3",
      "damage": "-",
      "notes": "-",
      "oki": "-",
      "volunteer": "-",
      "volunteer twitter": "-"
    },
    {
      "starter": "Wall Ender",
      "combo": "d/b+4, 4",
      "damage": "-",
      "notes": "-",
      "oki": "-",
      "volunteer": "-",
      "volunteer twitter": "-"
    }
  ]
}